{
  "id": "01028a117e8845ed90e1bc859ff6d4f3",
  "namespace": "f7e06ee3d0c1491094cc0215859f0120",
  "title": "Untitled Goose Game",
  "description": "Untitled Goose Game",
  "longDescription": null,
  "status": "ACTIVE",
  "productSlug": "untitled-goose-game/home",
  "urlSlug": "flourgeneralaudience",
  "creationDate": "2019-06-06T18:11:05.006Z",
  "lastModifiedDate": "2020-09-23T17:01:39.764Z",
  "effectiveDate": "2019-09-13T00:00:00.000Z",
  "viewableDate": null,
  "developer": null,
  "seller": {
    "id": "o-a62axwpwx275msq4yzhdhk9acaf8x3",
    "name": "Panic"
  },
  "linkedOfferId": null,
  "isFeatured": false,
  "ignoreOrder": false,
  "freeDays": 0,
  "collectionOfferIds": [],
  "technicalDetails": null,
  "recurrence": "ONCE",
  "categories": [
    {
      "path": "games"
    },
    {
      "path": "games/edition/base"
    },
    {
      "path": "games/edition"
    },
    {
      "path": "applications"
    }
  ],
  "tags": [
    {
      "id": "1298",
      "name": "PUZZLE",
      "namespace": "epic",
      "aliases": null,
      "operator": null,
      "created": "2019-06-20T12:00:46.616Z",
      "updated": "2020-09-09T02:28:11.779Z",
      "status": "ACTIVE",
      "referenceCount": 27,
      "comment": null
    },
    null,
    {
      "id": "9547",
      "name": "WINDOWS",
      "namespace": "epic",
      "aliases": [],
      "operator": "kimberly.rodatos",
      "created": "2019-10-11T02:43:18.435Z",
      "updated": "2020-09-16T23:47:27.310Z",
      "status": "ACTIVE",
      "referenceCount": 259,
      "comment": null
    },
    {
      "id": "1116",
      "name": "COMEDY",
      "namespace": "epic",
      "aliases": null,
      "operator": null,
      "created": "2019-06-20T11:59:16.126Z",
      "updated": "2020-09-03T15:08:30.761Z",
      "status": "ACTIVE",
      "referenceCount": 8,
      "comment": null
    },
    {
      "id": "1084",
      "name": "STEALTH",
      "namespace": "epic",
      "aliases": null,
      "operator": null,
      "created": "2019-06-20T11:59:00.299Z",
      "updated": "2020-09-15T15:54:08.343Z",
      "status": "ACTIVE",
      "referenceCount": 9,
      "comment": null
    }
  ],
  "customAttributes": [
    {
      "key": "com.epicgames.app.blacklist",
      "value": "{}"
    },
    {
      "key": "publisherName",
      "value": "Panic"
    },
    {
      "key": "developerName",
      "value": "House House"
    },
    {
      "key": "com.epicgames.app.productSlug",
      "value": "untitled-goose-game/home"
    }
  ],
  "keyImages": [
    {
      "type": "OfferImageWide",
      "url": "https://cdn1.epicgames.com/f7e06ee3d0c1491094cc0215859f0120/offer/EGS_UntitledGooseGame_HouseHouse_S1-2560x1440-a6da5a88af3101619d422edd66117960.jpg",
      "md5": "a6da5a88af3101619d422edd66117960",
      "size": 992708,
      "uploadedDate": "2020-09-23T17:00:44.728Z",
      "width": 2560,
      "height": 1440
    },
    {
      "type": "OfferImageTall",
      "url": "https://cdn1.epicgames.com/f7e06ee3d0c1491094cc0215859f0120/offer/EGS_UntitledGooseGame_HouseHouse_S2-1200x1600-81cd84044b7cf9825c44841e0671d227.jpg",
      "md5": "81cd84044b7cf9825c44841e0671d227",
      "size": 820114,
      "uploadedDate": "2020-09-23T17:00:57.102Z",
      "width": 1200,
      "height": 1600
    },
    {
      "type": "Thumbnail",
      "url": "https://cdn1.epicgames.com/f7e06ee3d0c1491094cc0215859f0120/offer/EGS_UntitledGooseGame_HouseHouse_S2-1200x1600-81cd84044b7cf9825c44841e0671d227.jpg",
      "md5": "81cd84044b7cf9825c44841e0671d227",
      "size": 820114,
      "uploadedDate": "2020-09-23T17:01:05.959Z",
      "width": 1200,
      "height": 1600
    },
    {
      "type": "CodeRedemption_340x440",
      "url": "https://cdn1.epicgames.com/f7e06ee3d0c1491094cc0215859f0120/offer/EGS_UntitledGooseGame_HouseHouse_S2-1200x1600-81cd84044b7cf9825c44841e0671d227.jpg",
      "md5": "81cd84044b7cf9825c44841e0671d227",
      "size": 820114,
      "uploadedDate": "2020-09-23T17:01:17.385Z",
      "width": 1200,
      "height": 1600
    },
    {
      "type": "DieselStoreFrontTall",
      "url": "https://cdn1.epicgames.com/f7e06ee3d0c1491094cc0215859f0120/offer/EGS_UntitledGooseGame_HouseHouse_S2-1200x1600-81cd84044b7cf9825c44841e0671d227.jpg",
      "md5": "81cd84044b7cf9825c44841e0671d227",
      "size": 820114,
      "uploadedDate": "2020-09-23T17:01:25.673Z",
      "width": 1200,
      "height": 1600
    },
    {
      "type": "DieselStoreFrontWide",
      "url": "https://cdn1.epicgames.com/f7e06ee3d0c1491094cc0215859f0120/offer/EGS_UntitledGooseGame_HouseHouse_S1-2560x1440-a6da5a88af3101619d422edd66117960.jpg",
      "md5": "a6da5a88af3101619d422edd66117960",
      "size": 992708,
      "uploadedDate": "2020-09-23T17:01:33.136Z",
      "width": 2560,
      "height": 1440
    }
  ],
  "items": [
    {
      "id": "0e32b4fcc5864bac9d45c3be90742bc8"
    }
  ],
  "catalogNs": null
}