{
  "id": "1115aa3a2827467eaf4f741ec6ab6606",
  "namespace": "6af58339c2424644988e0fb83dfd9bd5",
  "title": "Mark Ronson ft. Miley Cyrus - \"Nothing Breaks Like a Heart\"",
  "description": "Expand your FUSER™ library with \"Nothing Breaks Like a Heart\" by Mark Ronson ft. Miley Cyrus. Bring something new to your mixes with this additional playable track, available immediately in game.",
  "longDescription": "Expand your FUSER™ library with \"Nothing Breaks Like a Heart\" by Mark Ronson ft. Miley Cyrus. Bring something new to your mixes with this additional playable track, available immediately in game. Requires FUSER base game to play. For music credits, visit www.fuser.com.",
  "status": "ACTIVE",
  "productSlug": null,
  "urlSlug": "fuser--mark-ronson-miley-cyrus-nothing-breaks-like-a-heart",
  "creationDate": "2020-09-26T01:08:25.464Z",
  "lastModifiedDate": "2020-11-10T04:59:53.985Z",
  "effectiveDate": "2020-11-10T05:00:00.000Z",
  "viewableDate": null,
  "developer": null,
  "seller": {
    "id": "o-k8ltvz7rz3r7b29xdtafqvdkhnj2ux",
    "name": "NCSoft"
  },
  "linkedOfferId": null,
  "isFeatured": false,
  "ignoreOrder": false,
  "freeDays": 0,
  "collectionOfferIds": [],
  "technicalDetails": null,
  "recurrence": "ONCE",
  "categories": [
    {
      "path": "addons"
    },
    {
      "path": "addons/durable"
    },
    {
      "path": "applications"
    }
  ],
  "tags": [],
  "customAttributes": [
    {
      "key": "publisherName",
      "value": "NCSoft"
    },
    {
      "key": "developerName",
      "value": "Harmonix"
    }
  ],
  "keyImages": [
    {
      "type": "OfferImageWide",
      "url": "https://cdn1.epicgames.com/6af58339c2424644988e0fb83dfd9bd5/offer/EGS_FIXMarkRonsonftMileyCyrusNothingBr_Harmonix_DLC_S1-2560x1440-d8c983864c51b0009fc0ef586f81c281.jpg",
      "md5": "d8c983864c51b0009fc0ef586f81c281",
      "size": 593923,
      "uploadedDate": "2020-11-06T05:03:52.269Z",
      "width": 2560,
      "height": 1440
    },
    {
      "type": "OfferImageTall",
      "url": "https://cdn1.epicgames.com/6af58339c2424644988e0fb83dfd9bd5/offer/EGS_FIXMarkRonsonftMileyCyrusNothingBr_Harmonix_DLC_S2-1200x1600-951ecbe3cb027e91be4bf7d3ba05bbb6.jpg",
      "md5": "951ecbe3cb027e91be4bf7d3ba05bbb6",
      "size": 380280,
      "uploadedDate": "2020-11-06T05:03:55.151Z",
      "width": 1200,
      "height": 1600
    },
    {
      "type": "Thumbnail",
      "url": "https://cdn1.epicgames.com/6af58339c2424644988e0fb83dfd9bd5/offer/EGS_FIXMarkRonsonftMileyCyrusNothingBr_Harmonix_DLC_S2-1200x1600-951ecbe3cb027e91be4bf7d3ba05bbb6.jpg",
      "md5": "951ecbe3cb027e91be4bf7d3ba05bbb6",
      "size": 380280,
      "uploadedDate": "2020-11-06T05:03:57.825Z",
      "width": 1200,
      "height": 1600
    },
    {
      "type": "CodeRedemption_340x440",
      "url": "https://cdn1.epicgames.com/6af58339c2424644988e0fb83dfd9bd5/offer/EGS_FIXMarkRonsonftMileyCyrusNothingBr_Harmonix_DLC_S2-1200x1600-951ecbe3cb027e91be4bf7d3ba05bbb6.jpg",
      "md5": "951ecbe3cb027e91be4bf7d3ba05bbb6",
      "size": 380280,
      "uploadedDate": "2020-11-06T05:04:00.871Z",
      "width": 1200,
      "height": 1600
    }
  ],
  "items": [
    {
      "id": "03f6a99c5f6540beaac395453272f57a"
    }
  ],
  "catalogNs": null
}