{
  "id": "1516933c27344f478d04efa7ccaa623e",
  "namespace": "58c35a214bbb4656a536126ad1552d42",
  "title": "Death Coming",
  "description": "Death Coming",
  "longDescription": null,
  "status": "ACTIVE",
  "productSlug": "death-coming/home",
  "urlSlug": "burbotgeneralaudience",
  "creationDate": "2020-04-12T19:35:15.924Z",
  "lastModifiedDate": "2020-05-14T15:33:52.098Z",
  "effectiveDate": "2020-05-07T15:00:00.000Z",
  "viewableDate": "2020-04-30T15:00:00.000Z",
  "developer": null,
  "seller": {
    "id": "o-knwuvnlwzekqppkq2rj2snvys69l5g",
    "name": "Tencent Technology Company Limited"
  },
  "linkedOfferId": null,
  "isFeatured": false,
  "ignoreOrder": false,
  "freeDays": 0,
  "collectionOfferIds": [],
  "technicalDetails": null,
  "recurrence": "ONCE",
  "categories": [
    {
      "path": "games"
    },
    {
      "path": "games/edition/base"
    },
    {
      "path": "games/edition"
    },
    {
      "path": "applications"
    }
  ],
  "tags": [
    {
      "id": "1296",
      "name": "CASUAL",
      "namespace": "epic",
      "aliases": null,
      "operator": null,
      "created": "2019-06-20T12:00:45.644Z",
      "updated": "2020-07-29T14:19:01.050Z",
      "status": "ACTIVE",
      "referenceCount": 18,
      "comment": null
    },
    {
      "id": "1298",
      "name": "PUZZLE",
      "namespace": "epic",
      "aliases": null,
      "operator": null,
      "created": "2019-06-20T12:00:46.616Z",
      "updated": "2020-07-28T15:00:30.483Z",
      "status": "ACTIVE",
      "referenceCount": 27,
      "comment": null
    },
    {
      "id": "1370",
      "name": "SINGLEPLAYER",
      "namespace": "epic",
      "aliases": null,
      "operator": null,
      "created": "2019-06-20T12:01:22.169Z",
      "updated": "2020-07-29T20:28:51.499Z",
      "status": "ACTIVE",
      "referenceCount": 195,
      "comment": null
    },
    {
      "id": "1115",
      "name": "STRATEGY",
      "namespace": "epic",
      "aliases": null,
      "operator": null,
      "created": "2019-06-20T11:59:15.641Z",
      "updated": "2020-07-29T20:14:32.110Z",
      "status": "ACTIVE",
      "referenceCount": 33,
      "comment": null
    },
    {
      "id": "11631",
      "name": "REQUIRES 2FA",
      "namespace": null,
      "aliases": [],
      "operator": "Jason Savage",
      "created": "2020-04-29T16:18:12.784Z",
      "updated": "2020-07-29T19:40:33.650Z",
      "status": "ACTIVE",
      "referenceCount": 5,
      "comment": "Tag used to denote that this product will require the user to have 2 factor authentication enabled"
    }
  ],
  "customAttributes": [
    {
      "key": "com.epicgames.app.blacklist",
      "value": "[]"
    },
    {
      "key": "publisherName",
      "value": "NExT Studios"
    },
    {
      "key": "com.epicgames.app.productSlug",
      "value": "death-coming/home"
    }
  ],
  "keyImages": [
    {
      "type": "OfferImageWide",
      "url": "https://cdn1.epicgames.com/58c35a214bbb4656a536126ad1552d42/offer/EGS_DeathComing_NExTStudios_S1-2560x1440-7b1d3d39e3b37ced1633da45c010117d.jpg",
      "md5": "7b1d3d39e3b37ced1633da45c010117d",
      "size": 841096,
      "uploadedDate": "2020-04-15T21:03:10.807Z",
      "width": 2560,
      "height": 1440
    },
    {
      "type": "OfferImageTall",
      "url": "https://cdn1.epicgames.com/58c35a214bbb4656a536126ad1552d42/offer/EGS_DeathComing_NExTStudios_S2-860x1148-8fcfbb18c34364f804e5b79d8e23f590.jpg",
      "md5": "8fcfbb18c34364f804e5b79d8e23f590",
      "size": 341540,
      "uploadedDate": "2020-04-15T21:03:26.826Z",
      "width": 860,
      "height": 1148
    },
    {
      "type": "Thumbnail",
      "url": "https://cdn1.epicgames.com/58c35a214bbb4656a536126ad1552d42/offer/EGS_DeathComing_NExTStudios_S2-860x1148-8fcfbb18c34364f804e5b79d8e23f590.jpg",
      "md5": "8fcfbb18c34364f804e5b79d8e23f590",
      "size": 341540,
      "uploadedDate": "2020-04-15T21:03:41.096Z",
      "width": 860,
      "height": 1148
    },
    {
      "type": "DieselStoreFrontWide",
      "url": "https://cdn1.epicgames.com/58c35a214bbb4656a536126ad1552d42/offer/EGS_DeathComing_NExTStudios_S1-2560x1440-7b1d3d39e3b37ced1633da45c010117d.jpg",
      "md5": "7b1d3d39e3b37ced1633da45c010117d",
      "size": 841096,
      "uploadedDate": "2020-04-15T21:05:10.968Z",
      "width": 2560,
      "height": 1440
    },
    {
      "type": "DieselStoreFrontTall",
      "url": "https://cdn1.epicgames.com/58c35a214bbb4656a536126ad1552d42/offer/EGS_DeathComing_NExTStudios_S2-860x1148-8fcfbb18c34364f804e5b79d8e23f590.jpg",
      "md5": "8fcfbb18c34364f804e5b79d8e23f590",
      "size": 341540,
      "uploadedDate": "2020-04-15T21:05:23.935Z",
      "width": 860,
      "height": 1148
    }
  ],
  "items": [
    {
      "id": "0b1c8fccc0e248e29e363982a143c8d0"
    }
  ],
  "catalogNs": null
}