{
  "id": "19d333757fc7497ab364841603d2e410",
  "namespace": "ark",
  "title": "ARK Genesis Season Pass",
  "description": "Continue your quest for survival and unlock the next chapter in the saga of ARK: Survival Evolved with the ARK: Genesis Season Pass! Two new huge expansions: ARK: Genesis Part 1, ARK: Genesis Part 2 and one exclusive in-game robotic AI companion.",
  "longDescription": "Unlock a whole new chapter in ARK: Survival Evolved! This Season Pass gives access to two huge expansion packs that further the ARK storyline while adventuring through exotic new worlds with your robotic AI companion HLN-A’ in all-new mission-based gameplay.",
  "status": "ACTIVE",
  "productSlug": "ark/genesis-season-pass",
  "urlSlug": "ark--genesis-season-pass",
  "creationDate": "2020-05-11T23:31:26.315Z",
  "lastModifiedDate": "2020-07-31T23:23:00.552Z",
  "effectiveDate": "2020-06-11T15:00:00.000Z",
  "viewableDate": null,
  "developer": null,
  "seller": {
    "id": "o-usvfbmlqdt678vrp36qvm2d5cz2cpr",
    "name": "Studio Wildcard"
  },
  "linkedOfferId": null,
  "isFeatured": false,
  "ignoreOrder": false,
  "freeDays": 0,
  "collectionOfferIds": [],
  "technicalDetails": null,
  "recurrence": "ONCE",
  "categories": [
    {
      "path": "addons"
    },
    {
      "path": "addons/durable"
    },
    {
      "path": "applications"
    }
  ],
  "tags": [
    {
      "id": "1367",
      "name": "RPG",
      "namespace": "epic",
      "aliases": null,
      "operator": null,
      "created": "2019-06-20T12:01:20.701Z",
      "updated": "2020-08-12T16:55:34.370Z",
      "status": "ACTIVE",
      "referenceCount": 43,
      "comment": null
    },
    null,
    {
      "id": "1370",
      "name": "SINGLEPLAYER",
      "namespace": "epic",
      "aliases": [],
      "operator": null,
      "created": "2019-06-20T12:01:22.169Z",
      "updated": "2020-08-12T16:55:34.429Z",
      "status": "ACTIVE",
      "referenceCount": 195,
      "comment": null
    },
    {
      "id": "9547",
      "name": "WINDOWS",
      "namespace": "epic",
      "aliases": [],
      "operator": "kimberly.rodatos",
      "created": "2019-10-11T02:43:18.435Z",
      "updated": "2020-08-12T23:34:15.586Z",
      "status": "ACTIVE",
      "referenceCount": 259,
      "comment": null
    }
  ],
  "customAttributes": [
    {
      "key": "com.epicgames.app.blacklist",
      "value": "[]"
    },
    {
      "key": "publisherName",
      "value": "Snail Games USA"
    },
    {
      "key": "developerName",
      "value": "Studio Wildcard"
    },
    {
      "key": "com.epicgames.app.productSlug",
      "value": "ark/genesis-season-pass"
    }
  ],
  "keyImages": [
    {
      "type": "OfferImageWide",
      "url": "https://cdn1.epicgames.com/ark/offer/EGS_ARKGenesisSeasonPass_StudioWildcard_SeasonPass_S1-2560x1440-1dff4f517cccbfffa5d66d12a9b8acc6.jpg",
      "md5": "1dff4f517cccbfffa5d66d12a9b8acc6",
      "size": 999161,
      "uploadedDate": "2020-06-01T16:28:14.673Z",
      "width": 2560,
      "height": 1440
    },
    {
      "type": "OfferImageTall",
      "url": "https://cdn1.epicgames.com/ark/offer/EGS_ARKGenesisSeasonPass_StudioWildcard_SeasonPass_S2-1200x1600-769c735a6bafd98eef937cd391bff8e0.jpg",
      "md5": "769c735a6bafd98eef937cd391bff8e0",
      "size": 1019043,
      "uploadedDate": "2020-06-01T16:28:27.148Z",
      "width": 1200,
      "height": 1600
    },
    {
      "type": "Thumbnail",
      "url": "https://cdn1.epicgames.com/ark/offer/EGS_ARKGenesisSeasonPass_StudioWildcard_SeasonPass_S2-1200x1600-769c735a6bafd98eef937cd391bff8e0.jpg",
      "md5": "769c735a6bafd98eef937cd391bff8e0",
      "size": 1019043,
      "uploadedDate": "2020-06-01T16:28:37.022Z",
      "width": 1200,
      "height": 1600
    },
    {
      "type": "CodeRedemption_340x440",
      "url": "https://cdn1.epicgames.com/ark/offer/EGS_ARKGenesisSeasonPass_StudioWildcard_SeasonPass_S2-1200x1600-769c735a6bafd98eef937cd391bff8e0.jpg",
      "md5": "769c735a6bafd98eef937cd391bff8e0",
      "size": 1019043,
      "uploadedDate": "2020-06-01T16:28:49.998Z",
      "width": 1200,
      "height": 1600
    }
  ],
  "items": [
    {
      "id": "cd487143cd9148de964a4965b660e110"
    }
  ],
  "catalogNs": null
}