{
  "id": "39a69623764b491ab84e1d090b716c51",
  "namespace": "19078740fbcc4eada59a5a4ae7b3724c",
  "title": "PenguinDevAudience",
  "description": "PenguinDevAudience",
  "longDescription": null,
  "status": "ACTIVE",
  "productSlug": null,
  "urlSlug": "penguindevaudience",
  "creationDate": "2019-07-08T13:17:31.814Z",
  "lastModifiedDate": "2019-09-27T23:49:50.834Z",
  "effectiveDate": "2099-01-01T00:00:00.000Z",
  "viewableDate": null,
  "developer": null,
  "seller": {
    "id": "o-hsgwu456e63dkkgskeusntg93gey48",
    "name": "KO_OP"
  },
  "linkedOfferId": null,
  "isFeatured": false,
  "ignoreOrder": true,
  "freeDays": 0,
  "collectionOfferIds": [],
  "technicalDetails": null,
  "recurrence": "ONCE",
  "categories": [
    {
      "path": "games"
    },
    {
      "path": "applications"
    }
  ],
  "tags": [],
  "customAttributes": [
    {
      "key": "com.epicgames.app.blacklist",
      "value": "{}"
    },
    {
      "key": "publisherName",
      "value": "Double Fine"
    },
    {
      "key": "developerName",
      "value": "Ko-Op"
    }
  ],
  "keyImages": [
    {
      "type": "Thumbnail",
      "url": "https://cdn1.epicgames.com/19078740fbcc4eada59a5a4ae7b3724c/offer/CodeRedemption_GNOG-340x440-deb4e24eac48ef2e8eb0d87d23a1727d.jpg",
      "md5": "deb4e24eac48ef2e8eb0d87d23a1727d",
      "size": 186046,
      "uploadedDate": "2019-07-29T18:52:25.494Z",
      "width": 340,
      "height": 440
    },
    {
      "type": "CodeRedemption_340x440",
      "url": "https://cdn1.epicgames.com/19078740fbcc4eada59a5a4ae7b3724c/offer/CodeRedemption_GNOG-340x440-deb4e24eac48ef2e8eb0d87d23a1727d.jpg",
      "md5": "deb4e24eac48ef2e8eb0d87d23a1727d",
      "size": 186046,
      "uploadedDate": "2019-07-29T18:52:44.129Z",
      "width": 340,
      "height": 440
    }
  ],
  "items": [
    {
      "id": "121a714c386c4ff88d99c5aeda2af441"
    }
  ],
  "catalogNs": null
}