{
  "isFeatured": false,
  "collectionOfferIds": [],
  "effectiveDate": "2099-01-01T00:00:00.000Z",
  "creationDate": "2019-11-21T22:58:40.263Z",
  "lastModifiedDate": "2020-06-24T19:06:23.591Z",
  "viewableDate": null,
  "productSlug": null,
  "developer": null,
  "ignoreOrder": false,
  "freeDays": 0,
  "title": "DLC 7",
  "id": "76d28e247cfd405abad6b1a033e76895",
  "namespace": "3542a1df211e492bb2abecb7c734f7f9",
  "description": "Man Down Under Cosmetic DLC",
  "longDescription": null,
  "status": "ACTIVE",
  "keyImages": [],
  "seller": {
    "id": "o-ufmrk5furrrxgsp5tdngefzt5rxdcn",
    "name": "Epic Dev Test Account"
  },
  "items": [
    {
      "id": "d63ff34a1b6044fea783b06c621da1be",
      "namespace": "3542a1df211e492bb2abecb7c734f7f9",
      "developer": null
    }
  ],
  "customAttributes": [],
  "categories": [
    {
      "path": "games"
    },
    {
      "path": "applications"
    }
  ],
  "linkedOfferId": null,
  "linkedOffer": null
}