{
  "id": "9bfcafd7efab4372b55d2a697b1956d1",
  "namespace": "b9def67e597b4be7a16146146a044d02",
  "title": "MechWarrior 5 Closed Beta",
  "description": "MechWarrior 5 Closed Beta",
  "longDescription": null,
  "status": "ACTIVE",
  "productSlug": null,
  "urlSlug": "mechwarrior-5-closed-beta",
  "creationDate": "2019-10-21T19:09:40.548Z",
  "lastModifiedDate": "2019-12-10T13:53:12.719Z",
  "effectiveDate": "2050-08-01T10:05:00.000Z",
  "viewableDate": null,
  "developer": null,
  "seller": {
    "id": "o-muad9pj32k67stc4ycpgpplwq84sgq",
    "name": "Piranha Games"
  },
  "linkedOfferId": null,
  "isFeatured": false,
  "ignoreOrder": false,
  "freeDays": 0,
  "collectionOfferIds": [],
  "technicalDetails": null,
  "recurrence": "ONCE",
  "categories": [
    {
      "path": "games"
    },
    {
      "path": "applications"
    }
  ],
  "tags": [],
  "customAttributes": [],
  "keyImages": [
    {
      "type": "CodeRedemption_340x440",
      "url": "https://cdn1.epicgames.com/b9def67e597b4be7a16146146a044d02/offer/CodeRedemption_MechWarrior5-340x440-d6fc9fca58586de5b9d250d60e09e698.jpg",
      "md5": "d6fc9fca58586de5b9d250d60e09e698",
      "size": 230668,
      "uploadedDate": "2019-10-21T19:10:59.825Z",
      "width": 340,
      "height": 440
    },
    {
      "type": "Thumbnail",
      "url": "https://cdn1.epicgames.com/b9def67e597b4be7a16146146a044d02/offer/CodeRedemption_MechWarrior5-340x440-d6fc9fca58586de5b9d250d60e09e698.jpg",
      "md5": "d6fc9fca58586de5b9d250d60e09e698",
      "size": 230668,
      "uploadedDate": "2019-10-21T19:11:09.478Z",
      "width": 340,
      "height": 440
    }
  ],
  "items": [
    {
      "id": "c67bc6eebd4c47db899443036a6eb1e3"
    }
  ],
  "catalogNs": null
}