{
  "id": "a06d54dd4eaa435897c0f6e51666e5d6",
  "namespace": "c749cd78da34408d8434a46271f4bb79",
  "title": "DevCobiaAudience",
  "description": "DevCobiaAudience",
  "longDescription": null,
  "status": "ACTIVE",
  "productSlug": null,
  "urlSlug": "devcobiaaudience",
  "creationDate": "2020-03-19T20:34:51.831Z",
  "lastModifiedDate": "2020-04-29T00:46:39.882Z",
  "effectiveDate": "2099-01-01T00:00:00.000Z",
  "viewableDate": null,
  "developer": null,
  "seller": {
    "id": "o-cjwnkas5rn476tzk72fbh2ftutnc2y",
    "name": "Santa Ragione"
  },
  "linkedOfferId": null,
  "isFeatured": false,
  "ignoreOrder": true,
  "freeDays": 0,
  "collectionOfferIds": [],
  "technicalDetails": null,
  "recurrence": "ONCE",
  "categories": [
    {
      "path": "games"
    },
    {
      "path": "applications"
    }
  ],
  "tags": [],
  "customAttributes": [
    {
      "key": "com.epicgames.app.blacklist",
      "value": "KR,CN"
    },
    {
      "key": "publisherName",
      "value": "[]"
    },
    {
      "key": "developerName",
      "value": "[]"
    }
  ],
  "keyImages": [],
  "items": [
    {
      "id": "f201d4ac069b4989b583413e112f5660"
    }
  ],
  "catalogNs": null
}