{
  "id": "b3a7ea2e333a49ab8a7c3d0aa1f31e5e",
  "namespace": "cobra",
  "title": "My Time at Portia",
  "description": "My Time at Portia",
  "longDescription": null,
  "status": "ACTIVE",
  "productSlug": "my-time-at-portia/home",
  "urlSlug": "cobrageneralaudience",
  "creationDate": "2019-01-04T19:48:37.020Z",
  "lastModifiedDate": "2020-05-14T15:00:00.595Z",
  "effectiveDate": "2019-01-15T18:30:00.000Z",
  "viewableDate": "2019-01-15T18:30:00.000Z",
  "developer": null,
  "seller": {
    "id": "o-uvtztrtfjdn3xgrwyhbuwwb5z42mbv",
    "name": "Team17 Digital Ltd"
  },
  "linkedOfferId": null,
  "isFeatured": false,
  "ignoreOrder": false,
  "freeDays": 0,
  "collectionOfferIds": [],
  "technicalDetails": null,
  "recurrence": "ONCE",
  "categories": [
    {
      "path": "games"
    },
    {
      "path": "games/edition/base"
    },
    {
      "path": "games/edition"
    },
    {
      "path": "applications"
    }
  ],
  "tags": [
    null,
    {
      "id": "1367",
      "name": "RPG",
      "namespace": "epic",
      "aliases": null,
      "operator": null,
      "created": "2019-06-20T12:01:20.701Z",
      "updated": "2020-09-04T15:29:09.471Z",
      "status": "ACTIVE",
      "referenceCount": 43,
      "comment": null
    },
    null,
    {
      "id": "1307",
      "name": "OPEN WORLD",
      "namespace": "epic",
      "aliases": null,
      "operator": null,
      "created": "2019-06-20T12:00:51.191Z",
      "updated": "2020-09-03T17:05:54.623Z",
      "status": "ACTIVE",
      "referenceCount": 32,
      "comment": null
    },
    {
      "id": "9547",
      "name": "WINDOWS",
      "namespace": "epic",
      "aliases": [],
      "operator": "kimberly.rodatos",
      "created": "2019-10-11T02:43:18.435Z",
      "updated": "2020-09-05T13:11:46.627Z",
      "status": "ACTIVE",
      "referenceCount": 259,
      "comment": null
    },
    {
      "id": "9549",
      "name": "CONTROLLER SUPPORT",
      "namespace": "epic",
      "aliases": [],
      "operator": "kimberly.rodatos",
      "created": "2019-10-11T02:43:42.533Z",
      "updated": "2020-09-03T22:04:55.389Z",
      "status": "ACTIVE",
      "referenceCount": 103,
      "comment": null
    }
  ],
  "customAttributes": [
    {
      "key": "com.epicgames.app.blacklist",
      "value": "{}"
    },
    {
      "key": "publisherName",
      "value": "Team17"
    },
    {
      "key": "developerName",
      "value": "Pathea Games"
    },
    {
      "key": "com.epicgames.app.productSlug",
      "value": "my-time-at-portia/home"
    }
  ],
  "keyImages": [
    {
      "type": "OfferImageTall",
      "url": "https://cdn1.epicgames.com/cobra/offer/My Time at Portia - Portrait Offer Image-860x1148-1912d331acdbcbaf7055eaf7798dd709.jpg",
      "md5": "1912d331acdbcbaf7055eaf7798dd709",
      "size": 495500,
      "uploadedDate": "2020-04-10T20:31:39.560Z",
      "width": 860,
      "height": 1148
    },
    {
      "type": "OfferImageWide",
      "url": "https://cdn1.epicgames.com/cobra/offer/My Time at Portia - Landscape Offer Image-2560x1440-1daa364c9b5754cc98ef9f1cc5d02ae5.jpg",
      "md5": "1daa364c9b5754cc98ef9f1cc5d02ae5",
      "size": 510738,
      "uploadedDate": "2020-04-10T20:31:51.950Z",
      "width": 2560,
      "height": 1440
    },
    {
      "type": "Thumbnail",
      "url": "https://cdn1.epicgames.com/cobra/offer/My Time at Portia - Portrait Offer Image-860x1148-1912d331acdbcbaf7055eaf7798dd709.jpg",
      "md5": "1912d331acdbcbaf7055eaf7798dd709",
      "size": 495500,
      "uploadedDate": "2020-04-10T20:32:04.413Z",
      "width": 860,
      "height": 1148
    },
    {
      "type": "CodeRedemption_340x440",
      "url": "https://cdn1.epicgames.com/cobra/offer/My Time at Portia - Portrait Offer Image-860x1148-1912d331acdbcbaf7055eaf7798dd709.jpg",
      "md5": "1912d331acdbcbaf7055eaf7798dd709",
      "size": 495500,
      "uploadedDate": "2020-04-10T20:32:15.101Z",
      "width": 860,
      "height": 1148
    },
    {
      "type": "DieselStoreFrontTall",
      "url": "https://cdn1.epicgames.com/cobra/offer/My Time at Portia - Portrait Offer Image-860x1148-1912d331acdbcbaf7055eaf7798dd709.jpg",
      "md5": "1912d331acdbcbaf7055eaf7798dd709",
      "size": 495500,
      "uploadedDate": "2020-04-10T20:32:27.628Z",
      "width": 860,
      "height": 1148
    },
    {
      "type": "DieselStoreFrontWide",
      "url": "https://cdn1.epicgames.com/cobra/offer/My Time at Portia - Landscape Offer Image-2560x1440-1daa364c9b5754cc98ef9f1cc5d02ae5.jpg",
      "md5": "1daa364c9b5754cc98ef9f1cc5d02ae5",
      "size": 510738,
      "uploadedDate": "2020-04-10T20:32:47.611Z",
      "width": 2560,
      "height": 1440
    }
  ],
  "items": [
    {
      "id": "b1162ac1867b41f2b043510a67c6b2b7"
    }
  ],
  "catalogNs": null
}