{
  "isFeatured": false,
  "collectionOfferIds": [],
  "effectiveDate": "2099-01-01T00:00:00.000Z",
  "creationDate": "2019-06-06T19:39:05.582Z",
  "lastModifiedDate": "2019-09-27T23:15:48.071Z",
  "viewableDate": null,
  "productSlug": null,
  "developer": null,
  "ignoreOrder": true,
  "freeDays": 0,
  "title": "SwanDevAudience",
  "id": "d063018bb5e2482f854cc1997de17f06",
  "namespace": "ff1cd8b38bda4f6281879c9bdb228ff1",
  "description": "SwanDevAudience",
  "longDescription": null,
  "status": "ACTIVE",
  "keyImages": [
    {
      "type": "CodeRedemption_340x440",
      "url": "https://cdn1.epicgames.com/ff1cd8b38bda4f6281879c9bdb228ff1/offer/CodeRedemption_Atomicrops-340x437-95735b33f8dc9f5500cc6bc1acd4016e.png"
    },
    {
      "type": "Thumbnail",
      "url": "https://cdn1.epicgames.com/ff1cd8b38bda4f6281879c9bdb228ff1/offer/CodeRedemption_Atomicrops-340x437-95735b33f8dc9f5500cc6bc1acd4016e.png"
    }
  ],
  "seller": {
    "id": "o-fay4ghw9hhamujs53rfhy83ffexb7k",
    "name": "Raw Fury"
  },
  "items": [
    {
      "id": "aaee7f6ca2ab4b9ab561fca5f0559b88",
      "namespace": "ff1cd8b38bda4f6281879c9bdb228ff1",
      "developer": null
    }
  ],
  "customAttributes": [
    {
      "key": "com.epicgames.app.blacklist",
      "value": "{}"
    },
    {
      "key": "publisherName",
      "value": "Raw Fury"
    },
    {
      "key": "developerName",
      "value": "Bird Bath Games"
    }
  ],
  "categories": [
    {
      "path": "games"
    },
    {
      "path": "applications"
    }
  ],
  "linkedOfferId": null,
  "linkedOffer": null
}