{
  "isFeatured": false,
  "collectionOfferIds": [],
  "effectiveDate": "2016-03-28T00:00:00.000Z",
  "creationDate": "2016-03-29T02:21:55.149Z",
  "lastModifiedDate": "2020-02-04T18:38:55.834Z",
  "viewableDate": null,
  "productSlug": null,
  "developer": null,
  "ignoreOrder": false,
  "freeDays": 0,
  "title": "Golden Gem Chest",
  "id": "d4964baa304d4d419be379d472a03bc9",
  "namespace": "wex",
  "description": "Golden Gem Chest",
  "longDescription": null,
  "status": "ACTIVE",
  "keyImages": [],
  "seller": {
    "id": "o-aa83a0a9bc45e98c80c1b1c9d92e9e",
    "name": "Epic Games"
  },
  "items": [
    {
      "id": "d0198f23861c483f8d1e4c5373bc02fa",
      "namespace": "wex",
      "developer": null
    }
  ],
  "customAttributes": [],
  "categories": [
    {
      "path": "mtx packages"
    }
  ],
  "linkedOfferId": null,
  "linkedOffer": null
}