{
  "id": "d59ab901add54aa7930949e8ec7b44ec",
  "namespace": "epic",
  "title": "Free Games",
  "description": "Free To Play",
  "longDescription": null,
  "status": "ACTIVE",
  "productSlug": "free-to-play",
  "urlSlug": "free-to-play",
  "creationDate": "2019-12-17T04:09:25.564Z",
  "lastModifiedDate": "2020-04-29T19:10:45.076Z",
  "effectiveDate": "2019-12-16T23:06:00.000Z",
  "viewableDate": null,
  "developer": null,
  "seller": {
    "id": "o-ufmrk5furrrxgsp5tdngefzt5rxdcn",
    "name": "Epic Dev Test Account"
  },
  "linkedOfferId": null,
  "isFeatured": false,
  "ignoreOrder": false,
  "freeDays": 0,
  "collectionOfferIds": [
    "32e2f79db2ce4c04a69c91b5c74b320f",
    "308d380d8b5d4141b59d8f1722150475",
    "295c4c70e3914d4691b15821071d8d4c",
    "417e1534b94047f585aa36f887c51eb1",
    "db50f262e26343c394c9a928ca725671",
    "f687b9ca6725409494d7ffba82d5abaf",
    "6f37f05b306b48cdbab3db5e50633ebe",
    "5e9b31ab1afa40c5a21d7ed3c1e4e49d"
  ],
  "technicalDetails": null,
  "recurrence": "ONCE",
  "categories": [
    {
      "path": "collections"
    }
  ],
  "tags": [],
  "customAttributes": [
    {
      "key": "com.epicgames.app.collectionOfferIds.8",
      "value": "5e9b31ab1afa40c5a21d7ed3c1e4e49d"
    },
    {
      "key": "com.epicgames.app.collectionOfferIds.1",
      "value": "32e2f79db2ce4c04a69c91b5c74b320f"
    },
    {
      "key": "com.epicgames.app.collectionOfferIds.3",
      "value": "295c4c70e3914d4691b15821071d8d4c"
    },
    {
      "key": "com.epicgames.app.collectionOfferIds.2",
      "value": "308d380d8b5d4141b59d8f1722150475"
    },
    {
      "key": "com.epicgames.app.collectionOfferIds.5",
      "value": "db50f262e26343c394c9a928ca725671"
    },
    {
      "key": "com.epicgames.app.collectionOfferIds.4",
      "value": "417e1534b94047f585aa36f887c51eb1"
    },
    {
      "key": "com.epicgames.app.collectionOfferIds.7",
      "value": "6f37f05b306b48cdbab3db5e50633ebe"
    },
    {
      "key": "com.epicgames.app.productSlug",
      "value": "free-to-play"
    },
    {
      "key": "com.epicgames.app.collectionOfferIds.6",
      "value": "f687b9ca6725409494d7ffba82d5abaf"
    }
  ],
  "keyImages": [],
  "items": [
    {
      "id": "83564e9426d44ce2bbbab6037b80354c"
    }
  ],
  "catalogNs": null
}