{
  "id": "fb577a54c34948d28ea54624fad0d375",
  "namespace": "6af58339c2424644988e0fb83dfd9bd5",
  "title": "Future - \"Mask Off\"",
  "description": "Expand your FUSER™ library with \"Mask Off\" by Future! Bring something new to your mixes with this additional playable track, available immediately in game.",
  "longDescription": "Expand your FUSER™ library with \"Mask Off\" by Future! Bring something new to your mixes with this additional playable track, available immediately in game. Requires FUSER base game to play. For music credits, visit www.fuser.com.",
  "status": "ACTIVE",
  "productSlug": null,
  "urlSlug": "maskoffaudience",
  "creationDate": "2020-09-26T01:21:09.285Z",
  "lastModifiedDate": "2020-12-03T16:59:03.585Z",
  "effectiveDate": "2020-12-03T17:00:00.000Z",
  "viewableDate": "2020-12-03T17:00:00.000Z",
  "developer": null,
  "seller": {
    "id": "o-k8ltvz7rz3r7b29xdtafqvdkhnj2ux",
    "name": "NCSoft"
  },
  "linkedOfferId": null,
  "isFeatured": false,
  "ignoreOrder": false,
  "freeDays": 0,
  "collectionOfferIds": [],
  "technicalDetails": null,
  "recurrence": "ONCE",
  "categories": [
    {
      "path": "addons"
    },
    {
      "path": "addons/durable"
    },
    {
      "path": "applications"
    }
  ],
  "tags": [],
  "customAttributes": [
    {
      "key": "com.epicgames.app.blacklist",
      "value": "[]"
    },
    {
      "key": "publisherName",
      "value": "NCSOFT"
    },
    {
      "key": "developerName",
      "value": "Harmonix"
    }
  ],
  "keyImages": [
    {
      "type": "OfferImageTall",
      "url": "https://cdn1.epicgames.com/6af58339c2424644988e0fb83dfd9bd5/offer/EGS_FutureMaskOff_HarmonixMusicSystemsInc_DLC_S2-1200x1600-da1f1b3b39eeab631ad7bfe96d20711e.jpg",
      "md5": "da1f1b3b39eeab631ad7bfe96d20711e",
      "size": 367268,
      "uploadedDate": "2020-12-02T17:25:52.551Z",
      "width": 1200,
      "height": 1600
    },
    {
      "type": "OfferImageWide",
      "url": "https://cdn1.epicgames.com/6af58339c2424644988e0fb83dfd9bd5/offer/EGS_FutureMaskOff_HarmonixMusicSystemsInc_DLC_S1-2560x1440-7862a911df6739976453e4805b3e1fbe.jpg",
      "md5": "7862a911df6739976453e4805b3e1fbe",
      "size": 592797,
      "uploadedDate": "2020-12-02T17:25:59.994Z",
      "width": 2560,
      "height": 1440
    },
    {
      "type": "Thumbnail",
      "url": "https://cdn1.epicgames.com/6af58339c2424644988e0fb83dfd9bd5/offer/EGS_FutureMaskOff_HarmonixMusicSystemsInc_DLC_S2-1200x1600-da1f1b3b39eeab631ad7bfe96d20711e.jpg",
      "md5": "da1f1b3b39eeab631ad7bfe96d20711e",
      "size": 367268,
      "uploadedDate": "2020-12-02T17:26:09.572Z",
      "width": 1200,
      "height": 1600
    },
    {
      "type": "CodeRedemption_340x440",
      "url": "https://cdn1.epicgames.com/6af58339c2424644988e0fb83dfd9bd5/offer/EGS_FutureMaskOff_HarmonixMusicSystemsInc_DLC_S2-1200x1600-da1f1b3b39eeab631ad7bfe96d20711e.jpg",
      "md5": "da1f1b3b39eeab631ad7bfe96d20711e",
      "size": 367268,
      "uploadedDate": "2020-12-02T17:26:16.172Z",
      "width": 1200,
      "height": 1600
    }
  ],
  "items": [
    {
      "id": "ce6c1dda948a4c73a83960efcac81052"
    }
  ],
  "catalogNs": null
}