{
  "id": "fe58358bb3104bd19da2cb820f8912a3",
  "namespace": "fn",
  "title": "Travis Scott pack",
  "description": "Travis Scott pack",
  "longDescription": null,
  "status": "ACTIVE",
  "productSlug": null,
  "urlSlug": "fn-cj-all",
  "creationDate": "2020-04-21T14:33:12.950Z",
  "lastModifiedDate": "2020-04-21T14:33:12.950Z",
  "effectiveDate": "2020-04-21T10:29:00.000Z",
  "viewableDate": null,
  "developer": null,
  "seller": {
    "id": "o-aa83a0a9bc45e98c80c1b1c9d92e9e",
    "name": "Epic Games"
  },
  "linkedOfferId": null,
  "isFeatured": false,
  "ignoreOrder": false,
  "freeDays": 0,
  "collectionOfferIds": [],
  "technicalDetails": null,
  "recurrence": "ONCE",
  "categories": [
    {
      "path": "testing"
    }
  ],
  "tags": [],
  "customAttributes": [],
  "keyImages": [],
  "items": [
    {
      "id": "23116ca8314c4d0e9b7196ce0efa33e9"
    },
    {
      "id": "1ae802d6b9ac47fd8277d9e822ffb2f4"
    },
    {
      "id": "124a3b15e4614e6ea5ecff3a05b03fe2"
    },
    {
      "id": "6539784e21a1431094c047bdcb46edd9"
    },
    {
      "id": "2bc5696adccb434b85714c01728e1b83"
    },
    {
      "id": "92b63e0784934204b01ba51ead8850ae"
    },
    {
      "id": "5f3945ef1a8f4a9b9a425e110b046d74"
    }
  ],
  "catalogNs": null
}